{
  "sections": {
    "cart-items": {
      "type": "main-cart-items",
      "settings": {
        "color_scheme": "",
        "padding_top": 36,
        "padding_bottom": 36
      }
    },
    "rich_text_mzk6ag": {
      "type": "rich-text",
      "blocks": {
        "heading_zryXDg": {
          "type": "heading",
          "settings": {
            "heading": "Before you checkout...",
            "heading_size": "h2"
          }
        },
        "text_8xgDtq": {
          "type": "text",
          "settings": {
            "text": "<p><strong>If you have a rural address <\/strong>please ensure you click the 'Rural Address' button on checkout so the right freight charge is calculated. You can check if your address is rural by clicking on <a href=\"https:\/\/nzcouriers.co.nz\/tools\/check-an-address\/\" target=\"_blank\"><strong>Address Checker<\/strong><\/a><strong>.<\/strong><\/p><p><strong>If you do not select the rural address option then your goods may be delayed until the correct charges have been paid.<\/strong><\/p><p><strong>Note: <\/strong>We do not deliver to Waiheke Island. Please contact us to discuss delivery and collection options with you.<\/p>"
          }
        }
      },
      "block_order": [
        "heading_zryXDg",
        "text_8xgDtq"
      ],
      "custom_css": [

      ],
      "settings": {
        "desktop_content_position": "left",
        "content_alignment": "left",
        "color_scheme": "",
        "full_width": true,
        "padding_top": 20,
        "padding_bottom": 20
      }
    },
    "cart-footer": {
      "type": "main-cart-footer",
      "blocks": {
        "subtotal": {
          "type": "subtotal",
          "settings": {
          }
        },
        "buttons": {
          "type": "buttons",
          "settings": {
          }
        }
      },
      "block_order": [
        "subtotal",
        "buttons"
      ],
      "settings": {
        "color_scheme": "scheme-1330bf84-9d22-4f56-8fd6-b4b20199153a",
        "padding_top": 40,
        "padding_bottom": 100
      }
    },
    "featured-collection": {
      "type": "featured-collection",
      "settings": {
        "title": "Featured collection",
        "heading_size": "h2",
        "description": "",
        "show_description": false,
        "description_style": "body",
        "collection": "all",
        "products_to_show": 4,
        "columns_desktop": 4,
        "full_width": false,
        "show_view_all": true,
        "view_all_style": "solid",
        "enable_desktop_slider": false,
        "color_scheme": "scheme-2",
        "image_ratio": "square",
        "image_shape": "default",
        "show_secondary_image": false,
        "show_vendor": false,
        "show_rating": false,
        "enable_quick_add": false,
        "columns_mobile": "2",
        "swipe_on_mobile": false,
        "padding_top": 100,
        "padding_bottom": 80
      }
    }
  },
  "order": [
    "cart-items",
    "rich_text_mzk6ag",
    "cart-footer",
    "featured-collection"
  ]
}
